datatool/__init__.py
datatool/cli.py
datatool/persister.py
nmwdidatatool-0.0.2.dist-info/LICENSE
nmwdidatatool-0.0.2.dist-info/METADATA
nmwdidatatool-0.0.2.dist-info/WHEEL
nmwdidatatool-0.0.2.dist-info/entry_points.txt
nmwdidatatool-0.0.2.dist-info/top_level.txt
nmwdidatatool-0.0.2.dist-info/RECORD
