Metadata-Version: 2.1
Name: nmwdidatatool
Version: 0.0.2
Summary: NMWDI Data Tool
Home-page: https://github.com/NMWDI/pysta
Author: Jake Ross
License: UNKNOWN
Platform: UNKNOWN
Classifier: Programming Language :: Python :: 3
Classifier: Operating System :: OS Independent
Requires-Python: >=3.6
License-File: LICENSE
Requires-Dist: cython
Requires-Dist: Click
Requires-Dist: requests
Requires-Dist: shapely
Requires-Dist: pyshp
Requires-Dist: pysta (>=0.0.28)
